nti.wsgi.cors-1.2.0-py3.10-nspkg.pth
nti/wsgi/__init__.py
nti/wsgi/cors/__init__.py
nti/wsgi/cors/cors.py
nti/wsgi/cors/tests/__init__.py
nti/wsgi/cors/tests/test_cors.py
nti.wsgi.cors-1.2.0.dist-info/AUTHORS
nti.wsgi.cors-1.2.0.dist-info/LICENSE
nti.wsgi.cors-1.2.0.dist-info/METADATA
nti.wsgi.cors-1.2.0.dist-info/WHEEL
nti.wsgi.cors-1.2.0.dist-info/entry_points.txt
nti.wsgi.cors-1.2.0.dist-info/namespace_packages.txt
nti.wsgi.cors-1.2.0.dist-info/top_level.txt
nti.wsgi.cors-1.2.0.dist-info/zip-safe
nti.wsgi.cors-1.2.0.dist-info/RECORD
