Metadata-Version: 2.1
Name: nti.wsgi.cors
Version: 1.2.0
Summary: Support for CORS in a WSGI environment
Home-page: https://github.com/OpenNTI/nti.wsgi.cors
Author: Jason Madden
Author-email: jason@nextthought.com
License: Apache
Keywords: wsgi cors
Classifier: Intended Audience :: Developers
Classifier: Natural Language :: English
Classifier: Operating System :: OS Independent
Classifier: License :: OSI Approved :: Apache Software License
Classifier: Programming Language :: Python :: 2
Classifier: Programming Language :: Python :: 2.7
Classifier: Programming Language :: Python :: 3
Classifier: Programming Language :: Python :: 3.6
Classifier: Programming Language :: Python :: 3.7
Classifier: Programming Language :: Python :: 3.8
Classifier: Programming Language :: Python :: 3.9
Classifier: Programming Language :: Python :: 3.10
Classifier: Programming Language :: Python :: 3.11
Classifier: Programming Language :: Python :: Implementation :: CPython
Classifier: Programming Language :: Python :: Implementation :: PyPy
License-File: LICENSE
License-File: AUTHORS
Requires-Dist: setuptools
Requires-Dist: greenlet ; platform_python_implementation == "CPython"
Provides-Extra: docs
Requires-Dist: Sphinx ; extra == 'docs'
Requires-Dist: repoze.sphinx.autointerface ; extra == 'docs'
Requires-Dist: nti.testing ; extra == 'docs'
Requires-Dist: Paste ; extra == 'docs'
Requires-Dist: WebTest ; extra == 'docs'
Requires-Dist: zope.testrunner ; extra == 'docs'
Requires-Dist: sphinx-rtd-theme ; (python_version < "3.6") and extra == 'docs'
Requires-Dist: furo ; (python_version >= "3.6") and extra == 'docs'
Provides-Extra: test
Requires-Dist: nti.testing ; extra == 'test'
Requires-Dist: Paste ; extra == 'test'
Requires-Dist: WebTest ; extra == 'test'
Requires-Dist: zope.testrunner ; extra == 'test'
